pymsprog/.DS_Store
pymsprog/.ipynb_checkpoints/pymsprog_tutorial-checkpoint.ipynb
pymsprog/__init__.py
pymsprog/data/.DS_Store
pymsprog/data/MSprog_toydata.xlsx
pymsprog/data/MSprog_toydata_relapses.csv
pymsprog/data/MSprog_toydata_visits.csv
pymsprog-1.0.3.dist-info/METADATA
pymsprog-1.0.3.dist-info/WHEEL
pymsprog-1.0.3.dist-info/RECORD
