Metadata-Version: 2.3
Name: pymsprog
Version: 1.0.3
Summary: 
Author: noemi.montobbio
Author-email: noemi.montobbio@gmail.com
Requires-Python: >=3.9,<4.0
Classifier: Programming Language :: Python :: 3
Classifier: Programming Language :: Python :: 3.9
Classifier: Programming Language :: Python :: 3.10
Classifier: Programming Language :: Python :: 3.11
Classifier: Programming Language :: Python :: 3.12
Classifier: Programming Language :: Python :: 3.13
Requires-Dist: numpy (>=1.26,<2.0)
Requires-Dist: pandas (>=2.3.0,<3.0.0)
